gwseq_io_pp/__init__.py
gwseq_io_pp/bbi_data_tree.py
gwseq_io_pp/bbi_data_values.py
gwseq_io_pp/bbi_headers.py
gwseq_io_pp/bbi_locs.py
gwseq_io_pp/bbi_reader.py
gwseq_io_pp/util.py
gwseq_io_pp-0.0.1.dist-info/licenses/LICENSE
gwseq_io_pp-0.0.1.dist-info/METADATA
gwseq_io_pp-0.0.1.dist-info/WHEEL
gwseq_io_pp-0.0.1.dist-info/top_level.txt
gwseq_io_pp-0.0.1.dist-info/RECORD
