Metadata-Version: 2.4
Name: gwseq_io_pp
Version: 0.0.1
Summary: Process BBI (bigWig/bigBed) and HiC files
Author-email: Arthur Gouhier <ajgouhier@gmail.com>
License-Expression: MIT
Project-URL: Repository, https://github.com/ajgouhier/gwseq_io
Requires-Python: >=3.8
License-File: LICENSE
Requires-Dist: numpy
Dynamic: license-file
